autonavsim2d/__init__.py
autonavsim2d/autonavsim2d.py
autonavsim2d/utils/__init__.py
autonavsim2d/utils/input_field.py
autonavsim2d/utils/logger.py
autonavsim2d/utils/pose.py
autonavsim2d/utils/pose_stamped.py
autonavsim2d/utils/pp_controller.py
autonavsim2d/utils/robot_model.py
autonavsim2d/utils/sdv_model.py
autonavsim2d/utils/utils.py
autonavsim2d/utils/assets/background.jpg
autonavsim2d/utils/assets/background2.jpg
autonavsim2d/utils/assets/bicycle_model.png
autonavsim2d/utils/assets/dashboard_heading.png
autonavsim2d/utils/assets/heading_arrow.png
autonavsim2d/utils/assets/logo.png
autonavsim2d/utils/assets/robot.png
autonavsim2d/utils/assets/robot_1.png
autonavsim2d/utils/assets/robot_circle.png
autonavsim2d/utils/assets/robot_circle_1.png
autonavsim2D-2.0.0.dist-info/LICENSE
autonavsim2D-2.0.0.dist-info/METADATA
autonavsim2D-2.0.0.dist-info/WHEEL
autonavsim2D-2.0.0.dist-info/top_level.txt
autonavsim2D-2.0.0.dist-info/RECORD
