Metadata-Version: 2.1
Name: autonavsim2D
Version: 2.0.0
Summary: This project provides a 2D simulation environment designed for the development and testing of path planning algorithms. It offers a flexible and interactive platform for researchers, developers, and hobbyists to experiment with various path planning strategies in a controlled virtual space.
Home-page: https://github.com/yendiDev/autonavsim2d
Author: Clinton Anani
Author-email: kceequan01@gmail.com
Project-URL: Bug Tracker, https://github.com/yendiDev/autonavsim2d/issues
Classifier: Programming Language :: Python :: 3
Classifier: License :: OSI Approved :: MIT License
Classifier: Operating System :: OS Independent
Requires-Python: >=3.6
License-File: LICENSE
